LICENSE.txt
README.md
copernic360_cli/__init__.py
copernic360_cli/__main__.py
copernic360_cli/public_options.py
copernic360_cli-1.2.7.dist-info/WHEEL
copernic360_cli-1.2.7.dist-info/entry_points.txt
copernic360_cli-1.2.7.dist-info/LICENSE.txt
copernic360_cli-1.2.7.dist-info/METADATA
copernic360_cli-1.2.7.dist-info/RECORD
