Metadata-Version: 2.1
Name: copernic360-cli
Version: 1.2.7
Summary: Command-line script for Kagenova's Copernic360 API
Home-page: https://kagenova.com/products/copernic360/
License: Apache-2.0
Author: Kagenova
Maintainer: Mayeul d'Avezac
Maintainer-email: mayeul.davezac@kagenova.com
Requires-Python: >=3.7.1,<4
Classifier: License :: OSI Approved :: Apache Software License
Classifier: Programming Language :: Python :: 3
Classifier: Programming Language :: Python :: 3.8
Classifier: Programming Language :: Python :: 3.9
Classifier: Programming Language :: Python :: 3.10
Classifier: Programming Language :: Python :: 3.11
Requires-Dist: click (>=8,<9)
Requires-Dist: requests (>=2.25.1,<3.0.0)
